{"cameraMode":{"drawMode":0,"name":"Shaded","section":"Shading Mode"},"sceneLighting":false,"audioPlay":false,"sceneViewState":{"showFog":true,"showMaterialUpdate":false,"showSkybox":false,"showFlares":true,"showImageEffects":true,"showParticleSystems":true},"in2DMode":false,"pivot":{"x":0.0019451752305030823,"y":0.10228413343429566,"z":0.0022134780883789064},"rotation":{"x":0.0024088756181299688,"y":0.9975426197052002,"z":-0.044318027794361117,"w":0.05421629920601845},"size":0.15867666900157929,"orthographic":false}